curcuma/__init__.py
curcuma/__main__.py
curcuma/ccm.py
curcuma/cli.py
curcuma/client.py
curcuma/config.py
curcuma/endpoint.py
curcuma/exceptions.py
curcuma/log.py
curcuma/endpoints/__init__.py
curcuma/endpoints/data_view2.py.old
curcuma/endpoints/cloud/__init__.py
curcuma/endpoints/cloud/billing_costs.py
curcuma/endpoints/cloud/deployment.py
curcuma/endpoints/cloud/traffic_filter.py
curcuma/endpoints/elasticsearch/API.md
curcuma/endpoints/elasticsearch/__init__.py
curcuma/endpoints/elasticsearch/api_key.py
curcuma/endpoints/elasticsearch/cluster.py
curcuma/endpoints/elasticsearch/cross_cluster_api_key.py
curcuma/endpoints/elasticsearch/data_stream.py
curcuma/endpoints/elasticsearch/ilm.py
curcuma/endpoints/elasticsearch/index_alias.py
curcuma/endpoints/elasticsearch/role_mapping.py
curcuma/endpoints/elasticsearch/snapshot.py
curcuma/endpoints/kibana/__init__.py
curcuma/endpoints/kibana/data_view.py
curcuma/endpoints/kibana/role.py
curcuma/endpoints/kibana/settings.py
curcuma/endpoints/kibana/space.py
curcuma/templates/cloud/deployment/azure-general-purpose-update.json.j2
curcuma/templates/cloud/deployment/azure-general-purpose.json.j2
curcuma/templates/cloud/deployment/base.json.j2
curcuma/templates/cloud/deployment/general-purpose.json.j2
curcuma/templates/elasticsearch/cross_cluster_api_key/full_permission.json.j2
curcuma/templates/elasticsearch/index_alias/subscription_filter.json.j2
curcuma/templates/elasticsearch/role_mapping/oidc.json.j2
curcuma/templates/kibana/data_view/base.json.j2
curcuma/templates/kibana/data_view/base2.json.j2
curcuma/templates/kibana/role/cross_cluster_local.json.j2
curcuma/templates/kibana/role/cross_cluster_remote.json.j2
curcuma/templates/kibana/role/kibana_base.json.j2
curcuma/templates/kibana/role/kibana_extended.json.j2
curcuma/templates/kibana/role/synthetics_setup.json.j2
curcuma/templates/kibana/role/synthetics_writer.json.j2
curcuma-0.0.4.dist-info/METADATA
curcuma-0.0.4.dist-info/WHEEL
curcuma-0.0.4.dist-info/entry_points.txt
curcuma-0.0.4.dist-info/licenses/LICENSE
curcuma-0.0.4.dist-info/RECORD
