Metadata-Version: 2.4
Name: curcuma
Version: 0.0.4
Summary: A elastic API wrapper.
Project-URL: Homepage, https://github.com/aruehl/curcuma
Project-URL: Issues, https://github.com/aruehl/curcuma/issues
Author-email: Andreas Rühl <curcuma@ahr-software.de>
License-Expression: Apache-2.0
License-File: LICENSE
Classifier: Development Status :: 3 - Alpha
Classifier: License :: OSI Approved :: Apache Software License
Classifier: Operating System :: OS Independent
Classifier: Programming Language :: Python :: 3
Classifier: Topic :: Software Development :: Libraries :: Python Modules
Classifier: Topic :: Utilities
Requires-Python: >=3.9
Requires-Dist: deepdiff>=8.5.0
Requires-Dist: httpx>=0.28.1
Requires-Dist: jinja2>=3.1.6
Requires-Dist: typer>=0.16.0
